Metadata-Version: 1.1
Name: import-resolve
Version: 0.1.4
Summary: Resolves pip imports in a python project
Home-page: https://github.com/PandaWhoCodes/import_resolve
Author: Thomas Ashish Cherian
Author-email: ufoundashish@gmail.com
License: MIT
Platform: any
Classifier: Development Status :: 4 - Beta
Classifier: Environment :: Console
Classifier: Intended Audience :: Developers
Classifier: License :: OSI Approved :: BSD License
Classifier: Operating System :: POSIX
Classifier: Operating System :: MacOS
Classifier: Operating System :: Unix
Classifier: Operating System :: Microsoft :: Windows
Classifier: Programming Language :: Python
Classifier: Programming Language :: Python :: 2
Classifier: Programming Language :: Python :: 3
Classifier: Topic :: Software Development :: Libraries :: Python Modules
